empix/__init__.py
empix/version.py
empix-0.0.9.dist-info/licenses/LICENSE
empix-0.0.9.dist-info/METADATA
empix-0.0.9.dist-info/WHEEL
empix-0.0.9.dist-info/top_level.txt
empix-0.0.9.dist-info/RECORD
