Metadata-Version: 2.4
Name: empix
Version: 0.0.9
Summary: Contains tools for analyzing electron microscopy data that are not available in ``hyperspy``.
Author-email: Matthew Fitzpatrick <matthew.rc.fitzpatrick@gmail.com>
Project-URL: Homepage, https://mrfitzpa.github.io/empix
Project-URL: Repository, https://github.com/mrfitzpa/empix
Keywords: hyperspy,microscopy,cropping,downsampling,resampling,azimuthal integration,annular integration
Classifier: License :: OSI Approved :: GNU General Public License v3 (GPLv3)
Classifier: Development Status :: 5 - Production/Stable
Classifier: Intended Audience :: Science/Research
Classifier: Programming Language :: Python
Classifier: Programming Language :: Python :: 3
Classifier: Programming Language :: Python :: 3.8
Classifier: Programming Language :: Python :: 3.9
Classifier: Programming Language :: Python :: 3.10
Classifier: Programming Language :: Python :: 3.11
Classifier: Programming Language :: Python :: 3.12
Classifier: Operating System :: OS Independent
Classifier: Natural Language :: English
Requires-Python: >=3.8
License-File: LICENSE
Requires-Dist: czekitout
Requires-Dist: fancytypes>=1.0.0
Requires-Dist: hyperspy
Requires-Dist: pyFAI
Requires-Dist: numba
Provides-Extra: tests
Requires-Dist: pytest-cov; extra == "tests"
Provides-Extra: examples
Requires-Dist: jupyter; extra == "examples"
Requires-Dist: ipympl; extra == "examples"
Provides-Extra: docs
Requires-Dist: sphinx<7; extra == "docs"
Requires-Dist: sphinx_rtd_theme; extra == "docs"
Requires-Dist: sphinx-autodoc-typehints; extra == "docs"
Requires-Dist: numpydoc; extra == "docs"
Requires-Dist: docutils; extra == "docs"
Provides-Extra: all
Requires-Dist: empix[docs,examples,tests]; extra == "all"
Dynamic: license-file
